todo_extractor/__init__.py
todo_extractor/cli.py
todo_extractor/todo_extractor.py
todo_extractor-0.2.2.dist-info/entry_points.txt
todo_extractor-0.2.2.dist-info/LICENSE
todo_extractor-0.2.2.dist-info/WHEEL
todo_extractor-0.2.2.dist-info/METADATA
todo_extractor-0.2.2.dist-info/RECORD
