Metadata-Version: 2.1
Name: todo_extractor
Version: 0.2.2
Summary: Extracts TODO: notes from source code.
Home-page: https://github.com/vikahl/todo-extractor
License: UNKNOWN
Author: Viktor Ahlqvist
Author-email: flit@site.rxbc.se
Requires-Python: >=3.6
Classifier: License :: OSI Approved :: GNU General Public License v3 or later (GPLv3+)
Classifier: Development Status :: 3 - Alpha
Classifier: Programming Language :: Python
Classifier: Programming Language :: Python :: 3
Classifier: Programming Language :: Python :: 3.6
Classifier: Programming Language :: Python :: 3.7
Classifier: Programming Language :: Python :: 3.8
Requires-Dist: pre-commit ; extra == "dev"
Requires-Dist: pytest ; extra == "test"
Requires-Dist: pytest-cov ; extra == "test"
Requires-Dist: pytest-mock ; extra == "test"
Requires-Dist: tox ; extra == "test"
Requires-Dist: black ; extra == "test"
Requires-Dist: pylint ; extra == "test"
Requires-Dist: mypy ; extra == "test"
Requires-Dist: isort[pyproject] ; extra == "test"
Provides-Extra: dev
Provides-Extra: test
